README.md
setup.cfg
setup.py
pydetector/__init__.py
pydetector/__main__.py
pydetector/ast2dict.py
pydetector/ast_checks.py
pydetector/cli.py
pydetector/detector.py
pydetector/regexp_checks.py
pydetector/version.py
pydetector_bblfsh.egg-info/PKG-INFO
pydetector_bblfsh.egg-info/SOURCES.txt
pydetector_bblfsh.egg-info/dependency_links.txt
pydetector_bblfsh.egg-info/entry_points.txt
pydetector_bblfsh.egg-info/requires.txt
pydetector_bblfsh.egg-info/top_level.txt