Metadata-Version: 1.1
Name: pydetector-bblfsh
Version: 0.14.3
Summary: Python command line application & package to guess the Python version of a file
Home-page: https://github.com/juanjux/python-pydetector
Author: Juanjo Alvarez
Author-email: juanjo@juanjoalvarez.net
License: Apache License 2.0
Download-URL: https://github.com/juanjux/python-pydetector/archive/0.14.3.tar.gz
Platform: UNKNOWN
Classifier: Development Status :: 4 - Beta
Classifier: Environment :: Console
Classifier: Intended Audience :: Developers
Classifier: Topic :: Software Development :: Compilers
Classifier: Topic :: Software Development :: Disassemblers
Classifier: Operating System :: OS Independent
Classifier: Programming Language :: Python :: 3
Classifier: Programming Language :: Python :: 3.5
